{"nm":"Loading","v":"5.9.6","fr":60,"ip":0,"op":60,"w":150,"h":100,"ddd":0,"markers":[],"assets":[],"layers":[{"ty":3,"ind":1965,"hd":false,"nm":"Loading - Null","st":0,"ip":0,"op":60,"bm":0,"ks":{"a":{"a":0,"k":[0,0]},"o":{"a":0,"k":100},"p":{"a":0,"k":[0,0]},"r":{"a":0,"k":0},"s":{"a":0,"k":[100,100]}}},{"ty":3,"ind":49920,"hd":false,"nm":"Ellipse 3 - Null","st":0,"ip":0,"op":60,"bm":0,"ks":{"a":{"a":0,"k":[0,0]},"o":{"a":0,"k":100},"p":{"a":1,"k":[{"t":0,"s":[105,50],"o":{"x":[0.4745],"y":[-0.2304]},"i":{"x":[0.0357],"y":[1.0897]},"ti":[0,0],"to":[0,0]},{"t":60,"s":[15,50]}]},"r":{"a":0,"k":0},"s":{"a":0,"k":[100,100]}},"parent":1965},{"ty":4,"ind":94734,"hd":false,"nm":"Loading - Mask","st":0,"ip":0,"op":60,"bm":0,"ks":{"a":{"a":0,"k":[0,0]},"p":{"a":0,"k":[0,0]},"s":{"a":0,"k":[100,100]},"r":{"a":0,"k":0},"o":{"a":0,"k":100}},"shapes":[{"ty":"sh","nm":"Path","hd":false,"ks":{"a":0,"k":{"c":true,"v":[[0,100],[0,0],[150,0],[150,100],[0,100]],"i":[[0,0],[0,0],[0,0],[0,0],[0,0]],"o":[[0,0],[0,0],[0,0],[0,0],[0,0]]}}},{"ty":"fl","o":{"a":0,"k":100},"c":{"a":0,"k":[0,1,0]},"nm":"Fill","hd":false,"r":1}],"td":1,"parent":1965},{"ty":4,"ind":26523,"hd":false,"nm":"Ellipse 3","st":0,"ip":0,"op":60,"bm":0,"ks":{"a":{"a":0,"k":[0,0]},"p":{"a":0,"k":[0,0]},"s":{"a":0,"k":[100,100]},"r":{"a":0,"k":0},"o":{"a":0,"k":100}},"shapes":[{"ty":"sh","nm":"Path","hd":false,"ks":{"a":0,"k":{"c":true,"v":[[25,12.5],[12.5,25],[0,12.5],[12.5,0],[25,12.5],[25,12.5]],"i":[[0,0],[6.9038,0],[0,6.9038],[-6.9037,0],[0,-6.9037],[0,0]],"o":[[0,6.9038],[-6.9037,0],[0,-6.9037],[6.9038,0],[0,0],[0,0]]}}},{"ty":"fl","o":{"a":0,"k":100},"c":{"a":0,"k":[0.984313725490196,0.7803921568627451,0.21176470588235294,1]},"nm":"Fill","hd":false,"r":1}],"parent":49920,"tt":1},{"ty":3,"ind":38391,"hd":false,"nm":"Ellipse 2 - Null","st":0,"ip":0,"op":60,"bm":0,"ks":{"a":{"a":0,"k":[0,0]},"o":{"a":0,"k":100},"p":{"a":1,"k":[{"t":0,"s":[60,50],"o":{"x":[0.4745],"y":[-0.2304]},"i":{"x":[0.0357],"y":[1.0897]},"ti":[0,0],"to":[0,0]},{"t":30,"s":[60,11],"o":{"x":[0.4745],"y":[-0.2304]},"i":{"x":[0.0357],"y":[1.0897]},"ti":[0,0],"to":[0,0]},{"t":60,"s":[60,50]}]},"r":{"a":0,"k":0},"s":{"a":0,"k":[100,100]}},"parent":1965},{"ty":4,"ind":94734,"hd":false,"nm":"Loading - Mask","st":0,"ip":0,"op":60,"bm":0,"ks":{"a":{"a":0,"k":[0,0]},"p":{"a":0,"k":[0,0]},"s":{"a":0,"k":[100,100]},"r":{"a":0,"k":0},"o":{"a":0,"k":100}},"shapes":[{"ty":"sh","nm":"Path","hd":false,"ks":{"a":0,"k":{"c":true,"v":[[0,100],[0,0],[150,0],[150,100],[0,100]],"i":[[0,0],[0,0],[0,0],[0,0],[0,0]],"o":[[0,0],[0,0],[0,0],[0,0],[0,0]]}}},{"ty":"fl","o":{"a":0,"k":100},"c":{"a":0,"k":[0,1,0]},"nm":"Fill","hd":false,"r":1}],"td":1,"parent":1965},{"ty":4,"ind":925,"hd":false,"nm":"Ellipse 2","st":0,"ip":0,"op":60,"bm":0,"ks":{"a":{"a":0,"k":[0,0]},"p":{"a":0,"k":[0,0]},"s":{"a":0,"k":[100,100]},"r":{"a":0,"k":0},"o":{"a":0,"k":100}},"shapes":[{"ty":"sh","nm":"Path","hd":false,"ks":{"a":0,"k":{"c":true,"v":[[25,12.5],[12.5,25],[0,12.5],[12.5,0],[25,12.5],[25,12.5]],"i":[[0,0],[6.9038,0],[0,6.9038],[-6.9037,0],[0,-6.9037],[0,0]],"o":[[0,6.9038],[-6.9037,0],[0,-6.9037],[6.9038,0],[0,0],[0,0]]}}},{"ty":"fl","o":{"a":0,"k":100},"c":{"a":0,"k":[0.984313725490196,0.7803921568627451,0.21176470588235294,1]},"nm":"Fill","hd":false,"r":1}],"parent":38391,"tt":1},{"ty":3,"ind":62129,"hd":false,"nm":"Ellipse 1 - Null","st":0,"ip":0,"op":60,"bm":0,"ks":{"a":{"a":0,"k":[0,0]},"o":{"a":0,"k":100},"p":{"a":1,"k":[{"t":0,"s":[15,50],"o":{"x":[0.4745],"y":[-0.2304]},"i":{"x":[0.0357],"y":[1.0897]},"ti":[0,0],"to":[0,0]},{"t":60,"s":[105,50]}]},"r":{"a":0,"k":0},"s":{"a":0,"k":[100,100]}},"parent":1965},{"ty":4,"ind":94734,"hd":false,"nm":"Loading - Mask","st":0,"ip":0,"op":60,"bm":0,"ks":{"a":{"a":0,"k":[0,0]},"p":{"a":0,"k":[0,0]},"s":{"a":0,"k":[100,100]},"r":{"a":0,"k":0},"o":{"a":0,"k":100}},"shapes":[{"ty":"sh","nm":"Path","hd":false,"ks":{"a":0,"k":{"c":true,"v":[[0,100],[0,0],[150,0],[150,100],[0,100]],"i":[[0,0],[0,0],[0,0],[0,0],[0,0]],"o":[[0,0],[0,0],[0,0],[0,0],[0,0]]}}},{"ty":"fl","o":{"a":0,"k":100},"c":{"a":0,"k":[0,1,0]},"nm":"Fill","hd":false,"r":1}],"td":1,"parent":1965},{"ty":4,"ind":75823,"hd":false,"nm":"Ellipse 1","st":0,"ip":0,"op":60,"bm":0,"ks":{"a":{"a":0,"k":[0,0]},"p":{"a":0,"k":[0,0]},"s":{"a":0,"k":[100,100]},"r":{"a":0,"k":0},"o":{"a":0,"k":100}},"shapes":[{"ty":"sh","nm":"Path","hd":false,"ks":{"a":0,"k":{"c":true,"v":[[25,12.5],[12.5,25],[0,12.5],[12.5,0],[25,12.5],[25,12.5]],"i":[[0,0],[6.9038,0],[0,6.9038],[-6.9037,0],[0,-6.9037],[0,0]],"o":[[0,6.9038],[-6.9037,0],[0,-6.9037],[6.9038,0],[0,0],[0,0]]}}},{"ty":"fl","o":{"a":0,"k":100},"c":{"a":0,"k":[0.984313725490196,0.7803921568627451,0.21176470588235294,1]},"nm":"Fill","hd":false,"r":1}],"parent":62129,"tt":1},{"ty":4,"ind":55225,"hd":false,"nm":"Loading","st":0,"ip":0,"op":60,"bm":0,"ks":{"a":{"a":0,"k":[0,0]},"p":{"a":0,"k":[0,0]},"s":{"a":0,"k":[100,100]},"r":{"a":0,"k":0},"o":{"a":0,"k":100}},"parent":1965,"shapes":[{"ty":"sh","nm":"Path","hd":false,"ks":{"a":0,"k":{"c":true,"v":[[0,100],[0,0],[150,0],[150,100],[0,100]],"i":[[0,0],[0,0],[0,0],[0,0],[0,0]],"o":[[0,0],[0,0],[0,0],[0,0],[0,0]]}}},{"ty":"fl","o":{"a":0,"k":100},"c":{"a":0,"k":[0.4549019607843137,0.1803921568627451,0.5686274509803921,1]},"nm":"Fill","hd":false,"r":1}]}],"meta":{"a":"","d":"","tc":"","g":"Aninix"}}